kiwoomde/__init__.py
kiwoomde/base.py
kiwoomde/handlers.py
kiwoomde/conf/__init__.py
kiwoomde/conf/_setup.py
kiwoomde/database/__init__.py
kiwoomde/database/collection.py
kiwoomde/database/mongo.py
kiwoomde/database/schema.py
kiwoomde/dba/__init__.py
kiwoomde/dba/_collectionList.py
kiwoomde/dba/modelList.py
kiwoomde/dba/rt.py
kiwoomde/models/__init__.py
kiwoomde/models/_derived.py
kiwoomde/models/_devguide.py
kiwoomde/models/_mandata.py
kiwoomde/models/_util.py
kiwoomde/models/base.py
kiwoomde/models/rt.py
kiwoomde/models/tr.py
kiwoomde/models/trading.py
kiwoomde/utils/__init__.py
kiwoomde/utils/dt.py
kiwoomde/utils/viewer.py
kiwoomde/utils/vparser.py
kiwoomde/workers/__init__.py
kiwoomde/workers/init_db.py
kiwoomde/workers/rt.py
kiwoomde/workers/trading.py
kiwoomdsc/__init__.py
kiwoomdsc/profit.py
kiwoomdsc/stat.py
kiwoomdsc/tradingtarget.py
kiwoomdsc/viewer.py
kiwoomdsc/vis.py
kiwoomdsc/datamodels/Chejan.py
kiwoomdsc/datamodels/Company.py
kiwoomdsc/datamodels/OPT10023.py
kiwoomdsc/datamodels/RTList.py
kiwoomdsc/datamodels/RTModel.py
kiwoomdsc/datamodels/TRList.py
kiwoomdsc/datamodels/TradingSourceRealData.py
kiwoomdsc/datamodels/__init__.py
kiwoomdsc/datamodels/base.py
kiwoomdsc/workers/__init__.py
KiwoomDE-0.5.1.dist-info/METADATA
KiwoomDE-0.5.1.dist-info/WHEEL
KiwoomDE-0.5.1.dist-info/top_level.txt
KiwoomDE-0.5.1.dist-info/RECORD
