Metadata-Version: 2.1
Name: KiwoomDE
Version: 0.5.1
Summary: Kiwoom Data Engineering
Home-page: https://github.com/innovata/KiwoomDE
Author: innovata sambong
Author-email: iinnovata@gmail.com
License: UNKNOWN
Platform: UNKNOWN
Classifier: Programming Language :: Python :: 3
Classifier: License :: OSI Approved :: MIT License
Classifier: Operating System :: OS Independent
Requires-Python: >=3.8
